{
  "date": "2024-07-02",
  "data": [
    {
      "eps": "$1.74",
      "surprise": "N/A",
      "time": "time-pre-market",
      "symbol": "MSM",
      "name": "MSC Industrial Direct Company, Inc.",
      "marketCap": "$4,438,740,171",
      "fiscalQuarterEnding": "May/2024",
      "epsForecast": "$1.33",
      "noOfEsts": "7"
    },
    {
      "eps": "$0.20",
      "surprise": "N/A",
      "time": "time-after-hours",
      "symbol": "SLP",
      "name": "Simulations Plus, Inc.",
      "marketCap": "$943,888,952",
      "fiscalQuarterEnding": "May/2024",
      "epsForecast": "$0.17",
      "noOfEsts": "1"
    },
    {
      "eps": "$0.67",
      "surprise": "N/A",
      "time": "time-pre-market",
      "symbol": "RDUS",
      "name": "Radius Recycling, Inc.",
      "marketCap": "$409,379,015",
      "fiscalQuarterEnding": "May/2024",
      "epsForecast": "($0.87)",
      "noOfEsts": "1"
    }
  ]
}